helloworld/__init__.py
helloworld/bla.py
helloworld/tests.py
test_package_ortega2247-0.5.dist-info/METADATA
test_package_ortega2247-0.5.dist-info/WHEEL
test_package_ortega2247-0.5.dist-info/top_level.txt
test_package_ortega2247-0.5.dist-info/RECORD
