Metadata-Version: 2.1
Name: test-package-ortega2247
Version: 0.5
Summary: The familiar example program in Python
Home-page: http://github.com/dbarnett/python-helloworld
Author: David Barnett
Author-email: davidbarnett2@gmail.com
License: BSD
Keywords: example documentation tutorial
Platform: UNKNOWN
